woodle/__init__.py
woodle/woodle.py
woodle-0.3.dist-info/METADATA
woodle-0.3.dist-info/WHEEL
woodle-0.3.dist-info/entry_points.txt
woodle-0.3.dist-info/top_level.txt
woodle-0.3.dist-info/RECORD
