Metadata-Version: 2.4
Name: Woodle
Version: 0.3
Summary: Outil pour trnsformer un fichier de notes Moodle en fichier SNW.
Home-page: https://github.com/Epithumia/Woodle
Requires-Dist: pandas
Requires-Dist: xlrd==1.2.0
Requires-Dist: openpyxl
Dynamic: description
Dynamic: description-content-type
Dynamic: home-page
Dynamic: requires-dist
Dynamic: summary
